my_provider/__init__.py
my_provider/hooks/__init__.py
my_provider/hooks/dlc_hook.py
my_provider/operators/__init__.py
my_provider/operators/dlc_operator.py
my_provider-0.1.11.dist-info/METADATA
my_provider-0.1.11.dist-info/WHEEL
my_provider-0.1.11.dist-info/entry_points.txt
my_provider-0.1.11.dist-info/top_level.txt
my_provider-0.1.11.dist-info/RECORD
