Metadata-Version: 2.1
Name: my-provider
Version: 0.1.11
Summary: UNKNOWN
Home-page: UNKNOWN
Author: UNKNOWN
Author-email: UNKNOWN
License: UNKNOWN
Platform: UNKNOWN
Requires-Dist: apache-airflow (>=2.0.0)
Requires-Dist: tencentcloud-sdk-python (>=3.0.901)
